getTrades/__init__.py
getTrades/config.ini
getTrades/getTrades.py
getTrades/resultset.json
gettrades-1.7.3.dist-info/METADATA
gettrades-1.7.3.dist-info/WHEEL
gettrades-1.7.3.dist-info/entry_points.txt
gettrades-1.7.3.dist-info/licenses/LICENSE
gettrades-1.7.3.dist-info/RECORD
