Metadata-Version: 2.4
Name: getTrades
Version: 1.7.3
Summary: A tool querying Bitvavo.com to retrieve all trades and calculate overall results
Author-email: Nico de Smidt <nico@ndsrf.eu>
License-Expression: MIT
License-File: LICENSE
Classifier: Operating System :: OS Independent
Classifier: Programming Language :: Python :: 3
Requires-Python: >=3.13.0
Requires-Dist: configparser-crypt==1.1.0
Requires-Dist: keyring==25.6.0
Requires-Dist: pandas==2.2.3
Requires-Dist: tabulate2==1.10.1
Requires-Dist: websockets==14.2
